sphinx_qt_documentation/__init__.py
sphinx_qt_documentation/utils.py
sphinx_qt_documentation-0.4.1.dist-info/LICENSE.txt
sphinx_qt_documentation-0.4.1.dist-info/METADATA
sphinx_qt_documentation-0.4.1.dist-info/WHEEL
sphinx_qt_documentation-0.4.1.dist-info/top_level.txt
sphinx_qt_documentation-0.4.1.dist-info/RECORD
