Metadata-Version: 2.1
Name: sphinx-qt-documentation
Version: 0.4.1
Summary: Plugin for proper resolve intersphinx references for Qt elements
Home-page: https://github.com/Czaki/sphinx-qt-documentation
Author: Grzegorz Bokota
Author-email: bokota@gmail.com
License: BSD-3-Clause
Keywords: Sphinx,Qt,PyQt5,PySide2,PyQt6,PySide6
Platform: Linux
Platform: Windows
Platform: MacOs
Classifier: Development Status :: 3 - Alpha
Classifier: License :: OSI Approved :: BSD License
Classifier: Operating System :: OS Independent
Classifier: Programming Language :: Python :: 3
Classifier: Programming Language :: Python :: 3 :: Only
Classifier: Programming Language :: Python :: 3.6
Classifier: Programming Language :: Python :: 3.7
Classifier: Programming Language :: Python :: 3.8
Classifier: Programming Language :: Python :: 3.9
Classifier: Programming Language :: Python :: 3.10
Classifier: Programming Language :: Python :: Implementation :: CPython
Requires-Python: >=3.6
License-File: LICENSE.txt
Requires-Dist: docutils
Requires-Dist: sphinx
Provides-Extra: dev
Requires-Dist: pre-commit ; extra == 'dev'
Provides-Extra: lint
Requires-Dist: black ; extra == 'lint'
Requires-Dist: flake8 ; extra == 'lint'
Requires-Dist: pylint ; extra == 'lint'
Provides-Extra: test
Requires-Dist: pytest (>=3.0.0) ; extra == 'test'
Requires-Dist: pytest-cov ; extra == 'test'
